{
  "POST": {
    "/base-svr/history/selectDeviceProTypeData": {
      "errorCode": 1,
      "record": {
        "code": 0,
        "message": null,
        "count": 0,
        "data": {
          "unitList": [
            {
              "deviceId": null,
              "deviceName": "温湿度传感器",
              "proTypeId": "32",
              "proType": 5003,
              "num": 1,
              "name": "温度",
              "unit": "℃",
              "subName": "temperature#1"
            },
            {
              "deviceId": null,
              "deviceName": "温湿度传感器",
              "proTypeId": "33",
              "proType": 5004,
              "num": 2,
              "name": "湿度",
              "unit": "%RH",
              "subName": "湿度2#2"
            }
          ],
          "deviceData": [
            {
              "湿度2#2": "51.92",
              "time": {
                "year": 124,
                "month": 2,
                "date": 25,
                "day": 1,
                "hours": 0,
                "minutes": 0,
                "seconds": 0,
                "time": 1711296000000,
                "timezoneOffset": -28800
              },
              "temperature#1": "17.65"
            },
            {
              "湿度2#2": "53.02",
              "time": {
                "year": 124,
                "month": 2,
                "date": 25,
                "day": 1,
                "hours": 1,
                "minutes": 0,
                "seconds": 0,
                "time": 1711299600000,
                "timezoneOffset": -28800
              },
              "temperature#1": "17.65"
            },
            {
              "湿度2#2": "50.82",
              "time": {
                "year": 124,
                "month": 2,
                "date": 25,
                "day": 1,
                "hours": 2,
                "minutes": 0,
                "seconds": 0,
                "time": 1711303200000,
                "timezoneOffset": -28800
              },
              "temperature#1": "18.67"
            },
            {
              "湿度2#2": "51.89",
              "time": {
                "year": 124,
                "month": 2,
                "date": 25,
                "day": 1,
                "hours": 3,
                "minutes": 0,
                "seconds": 0,
                "time": 1711306800000,
                "timezoneOffset": -28800
              },
              "temperature#1": "18.23"
            },
            {
              "湿度2#2": "51.13",
              "time": {
                "year": 124,
                "month": 2,
                "date": 25,
                "day": 1,
                "hours": 4,
                "minutes": 0,
                "seconds": 0,
                "time": 1711310400000,
                "timezoneOffset": -28800
              },
              "temperature#1": "19.5"
            },
            {
              "湿度2#2": "53.57",
              "time": {
                "year": 124,
                "month": 2,
                "date": 25,
                "day": 1,
                "hours": 5,
                "minutes": 0,
                "seconds": 0,
                "time": 1711314000000,
                "timezoneOffset": -28800
              },
              "temperature#1": "18.78"
            },
            {
              "湿度2#2": "54.14",
              "time": {
                "year": 124,
                "month": 2,
                "date": 25,
                "day": 1,
                "hours": 6,
                "minutes": 0,
                "seconds": 0,
                "time": 1711317600000,
                "timezoneOffset": -28800
              },
              "temperature#1": "18.79"
            },
            {
              "湿度2#2": "52.53",
              "time": {
                "year": 124,
                "month": 2,
                "date": 25,
                "day": 1,
                "hours": 7,
                "minutes": 0,
                "seconds": 0,
                "time": 1711321200000,
                "timezoneOffset": -28800
              },
              "temperature#1": "18.74"
            },
            {
              "湿度2#2": "53.39",
              "time": {
                "year": 124,
                "month": 2,
                "date": 25,
                "day": 1,
                "hours": 8,
                "minutes": 0,
                "seconds": 0,
                "time": 1711324800000,
                "timezoneOffset": -28800
              },
              "temperature#1": "18.94"
            },
            {
              "湿度2#2": "54.73",
              "time": {
                "year": 124,
                "month": 2,
                "date": 25,
                "day": 1,
                "hours": 9,
                "minutes": 0,
                "seconds": 0,
                "time": 1711328400000,
                "timezoneOffset": -28800
              },
              "temperature#1": "19.69"
            },
            {
              "湿度2#2": "52.15",
              "time": {
                "year": 124,
                "month": 2,
                "date": 25,
                "day": 1,
                "hours": 10,
                "minutes": 0,
                "seconds": 0,
                "time": 1711332000000,
                "timezoneOffset": -28800
              },
              "temperature#1": "19.38"
            },
            {
              "湿度2#2": "52.24",
              "time": {
                "year": 124,
                "month": 2,
                "date": 25,
                "day": 1,
                "hours": 11,
                "minutes": 0,
                "seconds": 0,
                "time": 1711335600000,
                "timezoneOffset": -28800
              },
              "temperature#1": "17.28"
            },
            {
              "湿度2#2": "55.84",
              "time": {
                "year": 124,
                "month": 2,
                "date": 25,
                "day": 1,
                "hours": 12,
                "minutes": 0,
                "seconds": 0,
                "time": 1711339200000,
                "timezoneOffset": -28800
              },
              "temperature#1": "18.42"
            },
            {
              "湿度2#2": "54.22",
              "time": {
                "year": 124,
                "month": 2,
                "date": 25,
                "day": 1,
                "hours": 13,
                "minutes": 0,
                "seconds": 0,
                "time": 1711342800000,
                "timezoneOffset": -28800
              },
              "temperature#1": "19.15"
            },
            {
              "湿度2#2": "52.58",
              "time": {
                "year": 124,
                "month": 2,
                "date": 25,
                "day": 1,
                "hours": 14,
                "minutes": 0,
                "seconds": 0,
                "time": 1711346400000,
                "timezoneOffset": -28800
              },
              "temperature#1": "18.01"
            },
            {
              "湿度2#2": "52.22",
              "time": {
                "year": 124,
                "month": 2,
                "date": 25,
                "day": 1,
                "hours": 15,
                "minutes": 0,
                "seconds": 0,
                "time": 1711350000000,
                "timezoneOffset": -28800
              },
              "temperature#1": "19"
            },
            {
              "湿度2#2": "52.1",
              "time": {
                "year": 124,
                "month": 2,
                "date": 25,
                "day": 1,
                "hours": 16,
                "minutes": 0,
                "seconds": 0,
                "time": 1711353600000,
                "timezoneOffset": -28800
              },
              "temperature#1": "18.95"
            },
            {
              "湿度2#2": null,
              "time": {
                "year": 124,
                "month": 2,
                "date": 25,
                "day": 1,
                "hours": 17,
                "minutes": 0,
                "seconds": 0,
                "time": 1711357200000,
                "timezoneOffset": -28800
              },
              "temperature#1": null
            },
            {
              "湿度2#2": null,
              "time": {
                "year": 124,
                "month": 2,
                "date": 25,
                "day": 1,
                "hours": 18,
                "minutes": 0,
                "seconds": 0,
                "time": 1711360800000,
                "timezoneOffset": -28800
              },
              "temperature#1": null
            },
            {
              "湿度2#2": null,
              "time": {
                "year": 124,
                "month": 2,
                "date": 25,
                "day": 1,
                "hours": 19,
                "minutes": 0,
                "seconds": 0,
                "time": 1711364400000,
                "timezoneOffset": -28800
              },
              "temperature#1": null
            },
            {
              "湿度2#2": null,
              "time": {
                "year": 124,
                "month": 2,
                "date": 25,
                "day": 1,
                "hours": 20,
                "minutes": 0,
                "seconds": 0,
                "time": 1711368000000,
                "timezoneOffset": -28800
              },
              "temperature#1": null
            },
            {
              "湿度2#2": null,
              "time": {
                "year": 124,
                "month": 2,
                "date": 25,
                "day": 1,
                "hours": 21,
                "minutes": 0,
                "seconds": 0,
                "time": 1711371600000,
                "timezoneOffset": -28800
              },
              "temperature#1": null
            },
            {
              "湿度2#2": null,
              "time": {
                "year": 124,
                "month": 2,
                "date": 25,
                "day": 1,
                "hours": 22,
                "minutes": 0,
                "seconds": 0,
                "time": 1711375200000,
                "timezoneOffset": -28800
              },
              "temperature#1": null
            },
            {
              "湿度2#2": null,
              "time": {
                "year": 124,
                "month": 2,
                "date": 25,
                "day": 1,
                "hours": 23,
                "minutes": 0,
                "seconds": 0,
                "time": 1711378800000,
                "timezoneOffset": -28800
              },
              "temperature#1": null
            }
          ]
        }
      }
    }
  }
}