{
  "POST": {
    "/base-svr/realValueAlarm/selectHistoryList": {
      "errorCode": 1,
      "record": [
        {
          "id": "7402c1cdfe384a39bc49fbfbacb2549b",
          "configId": "5f35d97f3dfd4e8abb36575a3e0d0251",
          "rank": 1,
          "rankName": "1级报警",
          "sensorValue": 29.54,
          "conditionType": 2,
          "firstValue": 20,
          "secondValue": null,
          "createTime": {
            "year": 124,
            "month": 1,
            "date": 29,
            "day": 4,
            "hours": 11,
            "minutes": 36,
            "seconds": 47,
            "time": 1709177807000,
            "timezoneOffset": -480
          },
          "userId": "1739b39ce0df4837979c0894abe46a10",
          "result": "1",
          "dealTime": {
            "year": 124,
            "month": 1,
            "date": 29,
            "day": 4,
            "hours": 13,
            "minutes": 58,
            "seconds": 24,
            "time": 1709186304000,
            "timezoneOffset": -480
          },
          "beDeal": 1,
          "configName": "二氧化碳浓度报警配置",
          "deviceName": "pm2.5传感器",
          "typeName": "PM2.5",
          "sensorName": null,
          "username": "kyd-test",
          "cause": "二氧化碳浓度过高",
          "suggestion": "开窗通风",
          "url": null,
          "deviceId": "Gims-device-03",
          "address": null,
          "userName": "kyd-test"
        },
        {
          "id": "35fdc7dfe9d7431a82a280d566f8c691",
          "configId": "5f35d97f3dfd4e8abb36575a3e0d0251",
          "rank": 1,
          "rankName": "1级报警",
          "sensorValue": 35.88,
          "conditionType": 2,
          "firstValue": 20,
          "secondValue": null,
          "createTime": {
            "year": 124,
            "month": 1,
            "date": 28,
            "day": 3,
            "hours": 15,
            "minutes": 15,
            "seconds": 52,
            "time": 1709104552000,
            "timezoneOffset": -480
          },
          "userId": null,
          "result": null,
          "dealTime": null,
          "beDeal": 0,
          "configName": "二氧化碳浓度报警配置",
          "deviceName": "pm2.5传感器",
          "typeName": "PM2.5",
          "sensorName": null,
          "username": null,
          "cause": "二氧化碳浓度过高",
          "suggestion": "开窗通风",
          "url": null,
          "deviceId": "Gims-device-03",
          "address": null,
          "userName": null
        },
        {
          "id": "e8cfde48c7464622b51c581d0747707f",
          "configId": "5f35d97f3dfd4e8abb36575a3e0d0251",
          "rank": 1,
          "rankName": "1级报警",
          "sensorValue": 26.25,
          "conditionType": 2,
          "firstValue": 20,
          "secondValue": null,
          "createTime": {
            "year": 124,
            "month": 1,
            "date": 28,
            "day": 3,
            "hours": 13,
            "minutes": 45,
            "seconds": 29,
            "time": 1709099129000,
            "timezoneOffset": -480
          },
          "userId": "1739b39ce0df4837979c0894abe46a10",
          "result": "11",
          "dealTime": {
            "year": 124,
            "month": 1,
            "date": 29,
            "day": 4,
            "hours": 11,
            "minutes": 33,
            "seconds": 21,
            "time": 1709177601000,
            "timezoneOffset": -480
          },
          "beDeal": 1,
          "configName": "二氧化碳浓度报警配置",
          "deviceName": "pm2.5传感器",
          "typeName": "PM2.5",
          "sensorName": null,
          "username": "kyd-test",
          "cause": "二氧化碳浓度过高",
          "suggestion": "开窗通风",
          "url": null,
          "deviceId": "Gims-device-03",
          "address": null,
          "userName": "kyd-test"
        },
        {
          "id": "f0a8495281df4eabbc0e7d80a925fd13",
          "configId": "5f35d97f3dfd4e8abb36575a3e0d0251",
          "rank": 1,
          "rankName": "1级报警",
          "sensorValue": 36.92,
          "conditionType": 2,
          "firstValue": 20,
          "secondValue": null,
          "createTime": {
            "year": 124,
            "month": 1,
            "date": 28,
            "day": 3,
            "hours": 13,
            "minutes": 35,
            "seconds": 26,
            "time": 1709098526000,
            "timezoneOffset": -480
          },
          "userId": "1739b39ce0df4837979c0894abe46a10",
          "result": "22222",
          "dealTime": {
            "year": 124,
            "month": 1,
            "date": 28,
            "day": 3,
            "hours": 13,
            "minutes": 41,
            "seconds": 29,
            "time": 1709098889000,
            "timezoneOffset": -480
          },
          "beDeal": 2,
          "configName": "二氧化碳浓度报警配置",
          "deviceName": "pm2.5传感器",
          "typeName": "PM2.5",
          "sensorName": null,
          "username": "kyd-test",
          "cause": "二氧化碳浓度过高",
          "suggestion": "开窗通风",
          "url": null,
          "deviceId": "Gims-device-03",
          "address": null,
          "userName": "kyd-test"
        },
        {
          "id": "3d36afcb495644a3b47aca495e61b55c",
          "configId": "5f35d97f3dfd4e8abb36575a3e0d0251",
          "rank": 1,
          "rankName": "1级报警",
          "sensorValue": 32.23,
          "conditionType": 2,
          "firstValue": 20,
          "secondValue": null,
          "createTime": {
            "year": 124,
            "month": 1,
            "date": 28,
            "day": 3,
            "hours": 13,
            "minutes": 20,
            "seconds": 22,
            "time": 1709097622000,
            "timezoneOffset": -480
          },
          "userId": "1739b39ce0df4837979c0894abe46a10",
          "result": "2222222222",
          "dealTime": {
            "year": 124,
            "month": 2,
            "date": 1,
            "day": 5,
            "hours": 8,
            "minutes": 57,
            "seconds": 6,
            "time": 1709254626000,
            "timezoneOffset": -480
          },
          "beDeal": 2,
          "configName": "二氧化碳浓度报警配置",
          "deviceName": "pm2.5传感器",
          "typeName": "PM2.5",
          "sensorName": null,
          "username": "kyd-test",
          "cause": "二氧化碳浓度过高",
          "suggestion": "开窗通风",
          "url": null,
          "deviceId": "Gims-device-03",
          "address": null,
          "userName": "kyd-test"
        },
        {
          "id": "d8a2694f85f44f70bdd2def9a5a83052",
          "configId": "5f35d97f3dfd4e8abb36575a3e0d0251",
          "rank": 1,
          "rankName": "1级报警",
          "sensorValue": 20.83,
          "conditionType": 2,
          "firstValue": 20,
          "secondValue": null,
          "createTime": {
            "year": 124,
            "month": 1,
            "date": 28,
            "day": 3,
            "hours": 13,
            "minutes": 15,
            "seconds": 21,
            "time": 1709097321000,
            "timezoneOffset": -480
          },
          "userId": "1739b39ce0df4837979c0894abe46a10",
          "result": "111111",
          "dealTime": {
            "year": 124,
            "month": 2,
            "date": 1,
            "day": 5,
            "hours": 8,
            "minutes": 56,
            "seconds": 56,
            "time": 1709254616000,
            "timezoneOffset": -480
          },
          "beDeal": 1,
          "configName": "二氧化碳浓度报警配置",
          "deviceName": "pm2.5传感器",
          "typeName": "PM2.5",
          "sensorName": null,
          "username": "kyd-test",
          "cause": "二氧化碳浓度过高",
          "suggestion": "开窗通风",
          "url": null,
          "deviceId": "Gims-device-03",
          "address": null,
          "userName": "kyd-test"
        },
        {
          "id": "462562a116aa46a69674cc06ef797392",
          "configId": "5f35d97f3dfd4e8abb36575a3e0d0251",
          "rank": 1,
          "rankName": "1级报警",
          "sensorValue": 32.17,
          "conditionType": 2,
          "firstValue": 20,
          "secondValue": null,
          "createTime": {
            "year": 124,
            "month": 1,
            "date": 28,
            "day": 3,
            "hours": 13,
            "minutes": 5,
            "seconds": 19,
            "time": 1709096719000,
            "timezoneOffset": -480
          },
          "userId": "1739b39ce0df4837979c0894abe46a10",
          "result": "1111",
          "dealTime": {
            "year": 124,
            "month": 1,
            "date": 28,
            "day": 3,
            "hours": 13,
            "minutes": 41,
            "seconds": 18,
            "time": 1709098878000,
            "timezoneOffset": -480
          },
          "beDeal": 1,
          "configName": "二氧化碳浓度报警配置",
          "deviceName": "pm2.5传感器",
          "typeName": "PM2.5",
          "sensorName": null,
          "username": "kyd-test",
          "cause": "二氧化碳浓度过高",
          "suggestion": "开窗通风",
          "url": null,
          "deviceId": "Gims-device-03",
          "address": null,
          "userName": "kyd-test"
        },
        {
          "id": "32d659b91002407cbe975af4f4fab2bc",
          "configId": "5f35d97f3dfd4e8abb36575a3e0d0251",
          "rank": 1,
          "rankName": "1级报警",
          "sensorValue": 25.28,
          "conditionType": 2,
          "firstValue": 20,
          "secondValue": null,
          "createTime": {
            "year": 124,
            "month": 1,
            "date": 28,
            "day": 3,
            "hours": 12,
            "minutes": 35,
            "seconds": 12,
            "time": 1709094912000,
            "timezoneOffset": -480
          },
          "userId": "1739b39ce0df4837979c0894abe46a10",
          "result": "111",
          "dealTime": {
            "year": 124,
            "month": 1,
            "date": 28,
            "day": 3,
            "hours": 13,
            "minutes": 41,
            "seconds": 13,
            "time": 1709098873000,
            "timezoneOffset": -480
          },
          "beDeal": 1,
          "configName": "二氧化碳浓度报警配置",
          "deviceName": "pm2.5传感器",
          "typeName": "PM2.5",
          "sensorName": null,
          "username": "kyd-test",
          "cause": "二氧化碳浓度过高",
          "suggestion": "开窗通风",
          "url": null,
          "deviceId": "Gims-device-03",
          "address": null,
          "userName": "kyd-test"
        },
        {
          "id": "0e918c7fffa84bb89db8fcf0217c0890",
          "configId": "5f35d97f3dfd4e8abb36575a3e0d0251",
          "rank": 1,
          "rankName": "1级报警",
          "sensorValue": 26.31,
          "conditionType": 2,
          "firstValue": 20,
          "secondValue": null,
          "createTime": {
            "year": 124,
            "month": 1,
            "date": 28,
            "day": 3,
            "hours": 12,
            "minutes": 30,
            "seconds": 10,
            "time": 1709094610000,
            "timezoneOffset": -480
          },
          "userId": "1739b39ce0df4837979c0894abe46a10",
          "result": "11111",
          "dealTime": {
            "year": 124,
            "month": 1,
            "date": 28,
            "day": 3,
            "hours": 13,
            "minutes": 41,
            "seconds": 22,
            "time": 1709098882000,
            "timezoneOffset": -480
          },
          "beDeal": 1,
          "configName": "二氧化碳浓度报警配置",
          "deviceName": "pm2.5传感器",
          "typeName": "PM2.5",
          "sensorName": null,
          "username": "kyd-test",
          "cause": "二氧化碳浓度过高",
          "suggestion": "开窗通风",
          "url": null,
          "deviceId": "Gims-device-03",
          "address": null,
          "userName": "kyd-test"
        },
        {
          "id": "f6671ada7f654684a5bfca2f75903dc2",
          "configId": "5f35d97f3dfd4e8abb36575a3e0d0251",
          "rank": 1,
          "rankName": "1级报警",
          "sensorValue": 28.38,
          "conditionType": 2,
          "firstValue": 20,
          "secondValue": null,
          "createTime": {
            "year": 124,
            "month": 1,
            "date": 28,
            "day": 3,
            "hours": 12,
            "minutes": 0,
            "seconds": 3,
            "time": 1709092803000,
            "timezoneOffset": -480
          },
          "userId": "1739b39ce0df4837979c0894abe46a10",
          "result": "1111",
          "dealTime": {
            "year": 124,
            "month": 1,
            "date": 28,
            "day": 3,
            "hours": 15,
            "minutes": 28,
            "seconds": 49,
            "time": 1709105329000,
            "timezoneOffset": -480
          },
          "beDeal": 1,
          "configName": "二氧化碳浓度报警配置",
          "deviceName": "pm2.5传感器",
          "typeName": "PM2.5",
          "sensorName": null,
          "username": "kyd-test",
          "cause": "二氧化碳浓度过高",
          "suggestion": "开窗通风",
          "url": null,
          "deviceId": "Gims-device-03",
          "address": null,
          "userName": "kyd-test"
        }
      ]
    }
  }
}