{
  "GET": {
    "/solution-svr/agms-factor/getTargetFactorList": {
      "errorCode": 1,
      "record": [
        {
          "id": "21d29106ef1a41de86d2690776159369",
          "name": "PM10",
          "itercodeid": "A34002",
          "standardscale": 0,
          "changescale": 2,
          "mir": 0,
          "ofact": 0,
          "molecular": 0,
          "factorteam": 0,
          "accesscode": 108,
          "standardunitid": "80b6974ecd3b40b189971121acd9ee6c",
          "changeunitid": "d1439b2659664717a746423d33aaffe3",
          "fvc": 0,
          "fvoc": 0,
          "chageration": 2,
          "standardvalue": 0,
          "containedfactor": null,
          "type": 1,
          "protypeid": 61,
          "proType": "5030",
          "mark": "PM10"
        },
        {
          "id": "2e24ee5964f14412b52e748e81ec3111",
          "name": "SO2",
          "itercodeid": "A21026",
          "standardscale": 1,
          "changescale": 1,
          "mir": null,
          "ofact": null,
          "molecular": null,
          "factorteam": 0,
          "accesscode": 101,
          "standardunitid": "80b6974ecd3b40b189971121acd9ee6c",
          "changeunitid": "d1439b2659664717a746423d33aaffe3",
          "fvc": null,
          "fvoc": null,
          "chageration": 1,
          "standardvalue": null,
          "containedfactor": null,
          "type": 1,
          "protypeid": 59,
          "proType": "5028",
          "mark": "SO2"
        },
        {
          "id": "5198a2bb1e5f43c1829da3b219cfbe80",
          "name": "CO",
          "itercodeid": "A21005",
          "standardscale": 0,
          "changescale": 0,
          "mir": 2,
          "ofact": 0,
          "molecular": 0,
          "factorteam": 0,
          "accesscode": 106,
          "standardunitid": "80b6974ecd3b40b189971121acd9ee6c",
          "changeunitid": "d1439b2659664717a746423d33aaffe3",
          "fvc": 0,
          "fvoc": 0,
          "chageration": 0,
          "standardvalue": 0,
          "containedfactor": null,
          "type": 1,
          "protypeid": 35,
          "proType": "5006",
          "mark": "CO"
        },
        {
          "id": "5fcbffc3c87f485dbc92aa00b393993b",
          "name": "PM25",
          "itercodeid": "A34004",
          "standardscale": 0,
          "changescale": 0,
          "mir": 0,
          "ofact": 0,
          "molecular": 0,
          "factorteam": 0,
          "accesscode": 121,
          "standardunitid": "80b6974ecd3b40b189971121acd9ee6c",
          "changeunitid": "d1439b2659664717a746423d33aaffe3",
          "fvc": 0,
          "fvoc": 0,
          "chageration": 0,
          "standardvalue": 0,
          "containedfactor": null,
          "type": 1,
          "protypeid": 39,
          "proType": "5010",
          "mark": "PM2.5"
        },
        {
          "id": "8ff1d409479b477e94618dd02acfd5b5",
          "name": "O3",
          "itercodeid": "A34011",
          "standardscale": 0,
          "changescale": 0,
          "mir": 0,
          "ofact": 0,
          "molecular": 0,
          "factorteam": 0,
          "accesscode": 108,
          "standardunitid": "80b6974ecd3b40b189971121acd9ee6c",
          "changeunitid": "80b6974ecd3b40b189971121acd9ee6c",
          "fvc": 0,
          "fvoc": 0,
          "chageration": 0,
          "standardvalue": 0,
          "containedfactor": null,
          "type": 1,
          "protypeid": 62,
          "proType": "5031",
          "mark": "O3"
        },
        {
          "id": "a36ccb2afc374ca6925fc05c8451511f",
          "name": "NO2",
          "itercodeid": "A21004",
          "standardscale": 0,
          "changescale": 0,
          "mir": 0,
          "ofact": 0,
          "molecular": 0,
          "factorteam": 1,
          "accesscode": 141,
          "standardunitid": "80b6974ecd3b40b189971121acd9ee6c",
          "changeunitid": "d1439b2659664717a746423d33aaffe3",
          "fvc": 0,
          "fvoc": 0,
          "chageration": 2,
          "standardvalue": 0,
          "containedfactor": null,
          "type": 1,
          "protypeid": 60,
          "proType": "5029",
          "mark": "NO2"
        }
      ]
    }
  }
}